{
  "sources": {
    "AdamStaya": {
      "checks": 6094,
      "consecutive_empty": 0,
      "consecutive_errors": 0,
      "last_checked_at": "2026-07-23T17:53:02.598406+00:00",
      "last_messages_count": 20,
      "last_problem_at": "2026-07-13T20:00:35.305104+00:00",
      "last_success_at": "2026-07-23T17:53:02.598406+00:00",
      "status": "ok",
      "successful_checks": 6093,
      "transport_outages": 2
    },
    "Artem1dacast": {
      "checks": 4006,
      "consecutive_empty": 0,
      "consecutive_errors": 0,
      "last_checked_at": "2026-07-23T17:53:02.600150+00:00",
      "last_messages_count": 11,
      "last_problem_at": "2026-07-20T00:00:08.160376+00:00",
      "last_success_at": "2026-07-23T17:53:02.600150+00:00",
      "status": "ok",
      "successful_checks": 4005
    },
    "Avtoritet06101": {
      "checks": 4006,
      "consecutive_empty": 0,
      "consecutive_errors": 0,
      "last_checked_at": "2026-07-23T17:53:02.600236+00:00",
      "last_messages_count": 20,
      "last_problem_at": "2026-07-22T05:44:59.944884+00:00",
      "last_success_at": "2026-07-23T17:53:02.600236+00:00",
      "status": "ok",
      "successful_checks": 4005
    },
    "BCLesports": {
      "checks": 4006,
      "consecutive_empty": 0,
      "consecutive_errors": 0,
      "last_checked_at": "2026-07-23T17:53:02.600254+00:00",
      "last_messages_count": 17,
      "last_success_at": "2026-07-23T17:53:02.600254+00:00",
      "status": "ok",
      "successful_checks": 4006
    },
    "BELKAKIBER": {
      "checks": 4006,
      "consecutive_empty": 0,
      "consecutive_errors": 0,
      "last_checked_at": "2026-07-23T17:53:02.600271+00:00",
      "last_messages_count": 11,
      "last_success_at": "2026-07-23T17:53:02.600271+00:00",
      "status": "ok",
      "successful_checks": 4006
    },
    "BetBoomPR": {
      "checks": 3944,
      "consecutive_empty": 0,
      "consecutive_errors": 0,
      "last_checked_at": "2026-07-23T17:53:02.601085+00:00",
      "last_messages_count": 19,
      "last_success_at": "2026-07-23T17:53:02.601085+00:00",
      "status": "ok",
      "successful_checks": 3944
    },
    "Blessmur_mlbb": {
      "checks": 4006,
      "consecutive_empty": 0,
      "consecutive_errors": 0,
      "last_checked_at": "2026-07-23T17:53:02.600287+00:00",
      "last_messages_count": 4,
      "last_success_at": "2026-07-23T17:53:02.600287+00:00",
      "status": "ok",
      "successful_checks": 4006
    },
    "Blindzonexbet": {
      "checks": 6094,
      "consecutive_empty": 0,
      "consecutive_errors": 0,
      "last_checked_at": "2026-07-23T17:53:02.598671+00:00",
      "last_messages_count": 19,
      "last_success_at": "2026-07-23T17:53:02.598671+00:00",
      "status": "ok",
      "successful_checks": 6094,
      "transport_outages": 2
    },
    "Breakevens": {
      "checks": 5895,
      "consecutive_empty": 0,
      "consecutive_errors": 0,
      "last_checked_at": "2026-07-23T17:53:02.599315+00:00",
      "last_messages_count": 18,
      "last_success_at": "2026-07-23T17:53:02.599315+00:00",
      "status": "ok",
      "successful_checks": 5895,
      "transport_outages": 2
    },
    "Cyberhero_mobilelegends": {
      "checks": 4006,
      "consecutive_empty": 0,
      "consecutive_errors": 0,
      "last_checked_at": "2026-07-23T17:53:02.600372+00:00",
      "last_messages_count": 20,
      "last_success_at": "2026-07-23T17:53:02.600372+00:00",
      "status": "ok",
      "successful_checks": 4006
    },
    "DayneezBet": {
      "checks": 6094,
      "consecutive_empty": 0,
      "consecutive_errors": 0,
      "last_checked_at": "2026-07-23T17:53:02.598689+00:00",
      "last_messages_count": 19,
      "last_success_at": "2026-07-23T17:53:02.598689+00:00",
      "status": "ok",
      "successful_checks": 6094,
      "transport_outages": 2
    },
    "EWC_betboom": {
      "checks": 5895,
      "consecutive_empty": 0,
      "consecutive_errors": 0,
      "last_checked_at": "2026-07-23T17:53:02.599369+00:00",
      "last_messages_count": 12,
      "last_success_at": "2026-07-23T17:53:02.599369+00:00",
      "status": "ok",
      "successful_checks": 5895,
      "transport_outages": 2
    },
    "EviLGrannY_WoT": {
      "checks": 4007,
      "consecutive_empty": 0,
      "consecutive_errors": 0,
      "last_checked_at": "2026-07-23T17:53:02.599817+00:00",
      "last_messages_count": 19,
      "last_success_at": "2026-07-23T17:53:02.599817+00:00",
      "status": "ok",
      "successful_checks": 4007
    },
    "False9Jersey": {
      "checks": 5895,
      "consecutive_empty": 0,
      "consecutive_errors": 0,
      "last_checked_at": "2026-07-23T17:53:02.599333+00:00",
      "last_messages_count": 4,
      "last_success_at": "2026-07-23T17:53:02.599333+00:00",
      "status": "ok",
      "successful_checks": 5895,
      "transport_outages": 2
    },
    "GromoZekaCS": {
      "checks": 4007,
      "consecutive_empty": 0,
      "consecutive_errors": 0,
      "last_checked_at": "2026-07-23T17:53:02.599957+00:00",
      "last_messages_count": 15,
      "last_success_at": "2026-07-23T17:53:02.599957+00:00",
      "status": "ok",
      "successful_checks": 4007
    },
    "IGMMLBB": {
      "checks": 4007,
      "consecutive_empty": 0,
      "consecutive_errors": 0,
      "last_checked_at": "2026-07-23T17:53:02.599992+00:00",
      "last_messages_count": 20,
      "last_problem_at": "2026-07-22T04:21:47.482082+00:00",
      "last_success_at": "2026-07-23T17:53:02.599992+00:00",
      "status": "ok",
      "successful_checks": 4006
    },
    "KRATtv": {
      "checks": 6094,
      "consecutive_empty": 0,
      "consecutive_errors": 0,
      "last_checked_at": "2026-07-23T17:53:02.598744+00:00",
      "last_messages_count": 19,
      "last_success_at": "2026-07-23T17:53:02.598744+00:00",
      "status": "ok",
      "successful_checks": 6094,
      "transport_outages": 2
    },
    "KeysieCloud": {
      "checks": 4006,
      "consecutive_empty": 0,
      "consecutive_errors": 0,
      "last_checked_at": "2026-07-23T17:53:02.600542+00:00",
      "last_messages_count": 11,
      "last_success_at": "2026-07-23T17:53:02.600542+00:00",
      "status": "ok",
      "successful_checks": 4006
    },
    "LPK_esport": {
      "checks": 4006,
      "consecutive_empty": 0,
      "consecutive_errors": 0,
      "last_checked_at": "2026-07-23T17:53:02.600640+00:00",
      "last_messages_count": 20,
      "last_success_at": "2026-07-23T17:53:02.600640+00:00",
      "status": "ok",
      "successful_checks": 4006
    },
    "LifeForSurf": {
      "checks": 4006,
      "consecutive_empty": 0,
      "consecutive_errors": 0,
      "last_checked_at": "2026-07-23T17:53:02.600593+00:00",
      "last_messages_count": 19,
      "last_success_at": "2026-07-23T17:53:02.600593+00:00",
      "status": "ok",
      "successful_checks": 4006
    },
    "LilCandyML": {
      "checks": 4006,
      "consecutive_empty": 0,
      "consecutive_errors": 0,
      "last_checked_at": "2026-07-23T17:53:02.600611+00:00",
      "last_messages_count": 19,
      "last_success_at": "2026-07-23T17:53:02.600611+00:00",
      "status": "ok",
      "successful_checks": 4006
    },
    "MARIOMAXTV": {
      "checks": 5768,
      "consecutive_empty": 0,
      "consecutive_errors": 0,
      "last_checked_at": "2026-07-23T17:53:02.599491+00:00",
      "last_messages_count": 17,
      "last_success_at": "2026-07-23T17:53:02.599491+00:00",
      "status": "ok",
      "successful_checks": 5768
    },
    "MPKBK2": {
      "checks": 4006,
      "consecutive_empty": 0,
      "consecutive_errors": 0,
      "last_checked_at": "2026-07-23T17:53:02.600760+00:00",
      "last_messages_count": 16,
      "last_success_at": "2026-07-23T17:53:02.600760+00:00",
      "status": "ok",
      "successful_checks": 4006
    },
    "NeretCast": {
      "checks": 6094,
      "consecutive_empty": 0,
      "consecutive_errors": 0,
      "last_checked_at": "2026-07-23T17:53:02.598424+00:00",
      "last_messages_count": 11,
      "last_problem_at": "2026-07-22T02:46:48.712912+00:00",
      "last_success_at": "2026-07-23T17:53:02.598424+00:00",
      "status": "ok",
      "successful_checks": 6092,
      "transport_outages": 2
    },
    "PAPAdota2": {
      "checks": 6094,
      "consecutive_empty": 0,
      "consecutive_errors": 0,
      "last_checked_at": "2026-07-23T17:53:02.598286+00:00",
      "last_messages_count": 18,
      "last_problem_at": "2026-07-19T04:15:10.911855+00:00",
      "last_success_at": "2026-07-23T17:53:02.598286+00:00",
      "status": "ok",
      "successful_checks": 6092,
      "transport_outages": 2
    },
    "PIVOVAR_Cast": {
      "checks": 2195,
      "consecutive_empty": 0,
      "consecutive_errors": 0,
      "last_checked_at": "2026-07-21T07:53:27.382988+00:00",
      "last_messages_count": 16,
      "last_success_at": "2026-07-21T07:53:27.382988+00:00",
      "status": "ok",
      "successful_checks": 2195
    },
    "RelaxCisBet": {
      "checks": 6094,
      "consecutive_empty": 0,
      "consecutive_errors": 0,
      "last_checked_at": "2026-07-23T17:53:02.598820+00:00",
      "last_messages_count": 19,
      "last_success_at": "2026-07-23T17:53:02.598820+00:00",
      "status": "ok",
      "successful_checks": 6094,
      "transport_outages": 2
    },
    "SashkaDestroyer": {
      "checks": 4006,
      "consecutive_empty": 0,
      "consecutive_errors": 0,
      "last_checked_at": "2026-07-23T17:53:02.600863+00:00",
      "last_messages_count": 20,
      "last_success_at": "2026-07-23T17:53:02.600863+00:00",
      "status": "ok",
      "successful_checks": 4006
    },
    "StrayDungeon228": {
      "checks": 6094,
      "consecutive_empty": 0,
      "consecutive_errors": 0,
      "last_checked_at": "2026-07-23T17:53:02.598442+00:00",
      "last_messages_count": 20,
      "last_problem_at": "2026-07-19T04:15:10.912036+00:00",
      "last_success_at": "2026-07-23T17:53:02.598442+00:00",
      "status": "ok",
      "successful_checks": 6092,
      "transport_outages": 2
    },
    "Team_Spirit_Official": {
      "checks": 3432,
      "consecutive_empty": 0,
      "consecutive_errors": 0,
      "last_checked_at": "2026-07-23T17:53:02.601119+00:00",
      "last_messages_count": 10,
      "last_problem_at": "2026-07-23T00:56:41.682143+00:00",
      "last_success_at": "2026-07-23T17:53:02.601119+00:00",
      "status": "ok",
      "successful_checks": 3430
    },
    "VooDooSh_Stream": {
      "checks": 4006,
      "consecutive_empty": 0,
      "consecutive_errors": 0,
      "last_checked_at": "2026-07-23T17:53:02.600999+00:00",
      "last_messages_count": 20,
      "last_problem_at": "2026-07-20T00:00:08.161222+00:00",
      "last_success_at": "2026-07-23T17:53:02.600999+00:00",
      "status": "ok",
      "successful_checks": 4005
    },
    "XDZachQ": {
      "checks": 4007,
      "consecutive_empty": 0,
      "consecutive_errors": 0,
      "last_checked_at": "2026-07-23T17:53:02.600132+00:00",
      "last_messages_count": 19,
      "last_success_at": "2026-07-23T17:53:02.600132+00:00",
      "status": "ok",
      "successful_checks": 4007
    },
    "Xoma_cs": {
      "checks": 4006,
      "consecutive_empty": 0,
      "consecutive_errors": 0,
      "last_checked_at": "2026-07-23T17:53:02.601051+00:00",
      "last_messages_count": 9,
      "last_success_at": "2026-07-23T17:53:02.601051+00:00",
      "status": "ok",
      "successful_checks": 4006
    },
    "YBNFedor": {
      "checks": 5871,
      "consecutive_empty": 0,
      "consecutive_errors": 0,
      "last_checked_at": "2026-07-23T17:53:02.599122+00:00",
      "last_messages_count": 20,
      "last_success_at": "2026-07-23T17:53:02.599122+00:00",
      "status": "ok",
      "successful_checks": 5871
    },
    "ZZoneRM": {
      "checks": 6094,
      "consecutive_empty": 0,
      "consecutive_errors": 0,
      "last_checked_at": "2026-07-23T17:53:02.598911+00:00",
      "last_messages_count": 13,
      "last_success_at": "2026-07-23T17:53:02.598911+00:00",
      "status": "ok",
      "successful_checks": 6094,
      "transport_outages": 2
    },
    "acoolbazarit": {
      "checks": 6094,
      "consecutive_empty": 0,
      "consecutive_errors": 0,
      "last_checked_at": "2026-07-23T17:53:02.598555+00:00",
      "last_messages_count": 20,
      "last_success_at": "2026-07-23T17:53:02.598555+00:00",
      "status": "ok",
      "successful_checks": 6094,
      "transport_outages": 2
    },
    "adekvatik": {
      "checks": 5768,
      "consecutive_empty": 0,
      "consecutive_errors": 0,
      "last_checked_at": "2026-07-23T17:53:02.599509+00:00",
      "last_messages_count": 20,
      "last_success_at": "2026-07-23T17:53:02.599509+00:00",
      "status": "ok",
      "successful_checks": 5768
    },
    "alex_white_official": {
      "checks": 3432,
      "consecutive_empty": 0,
      "consecutive_errors": 0,
      "last_checked_at": "2026-07-23T17:53:02.601136+00:00",
      "last_messages_count": 20,
      "last_problem_at": "2026-07-22T07:42:26.994225+00:00",
      "last_success_at": "2026-07-23T17:53:02.601136+00:00",
      "status": "ok",
      "successful_checks": 3431
    },
    "amam0610": {
      "checks": 6094,
      "consecutive_empty": 0,
      "consecutive_errors": 0,
      "last_checked_at": "2026-07-23T17:53:02.599069+00:00",
      "last_messages_count": 20,
      "last_success_at": "2026-07-23T17:53:02.599069+00:00",
      "status": "ok",
      "successful_checks": 6094,
      "transport_outages": 2
    },
    "arszeeqq": {
      "checks": 4007,
      "consecutive_empty": 0,
      "consecutive_errors": 0,
      "last_checked_at": "2026-07-23T17:53:02.599698+00:00",
      "last_messages_count": 20,
      "last_success_at": "2026-07-23T17:53:02.599698+00:00",
      "status": "ok",
      "successful_checks": 4007
    },
    "artemkef": {
      "checks": 5895,
      "consecutive_empty": 0,
      "consecutive_errors": 0,
      "last_checked_at": "2026-07-23T17:53:02.599279+00:00",
      "last_messages_count": 19,
      "last_success_at": "2026-07-23T17:53:02.599279+00:00",
      "status": "ok",
      "successful_checks": 5895,
      "transport_outages": 2
    },
    "aterionlegends": {
      "checks": 4006,
      "consecutive_empty": 0,
      "consecutive_errors": 0,
      "last_checked_at": "2026-07-23T17:53:02.600167+00:00",
      "last_messages_count": 20,
      "last_success_at": "2026-07-23T17:53:02.600167+00:00",
      "status": "ok",
      "successful_checks": 4006
    },
    "aunkereEZ": {
      "checks": 6094,
      "consecutive_empty": 0,
      "consecutive_errors": 0,
      "last_checked_at": "2026-07-23T17:53:02.598369+00:00",
      "last_messages_count": 19,
      "last_problem_at": "2026-07-19T04:15:10.911959+00:00",
      "last_success_at": "2026-07-23T17:53:02.598369+00:00",
      "status": "ok",
      "successful_checks": 6092,
      "transport_outages": 2
    },
    "aunkeretg": {
      "checks": 6094,
      "consecutive_empty": 0,
      "consecutive_errors": 0,
      "last_checked_at": "2026-07-23T17:53:02.598929+00:00",
      "last_messages_count": 20,
      "last_success_at": "2026-07-23T17:53:02.598929+00:00",
      "status": "ok",
      "successful_checks": 6094,
      "transport_outages": 2
    },
    "autodestruction": {
      "checks": 4006,
      "consecutive_empty": 0,
      "consecutive_errors": 0,
      "last_checked_at": "2026-07-23T17:53:02.600184+00:00",
      "last_messages_count": 11,
      "last_success_at": "2026-07-23T17:53:02.600184+00:00",
      "status": "ok",
      "successful_checks": 4006
    },
    "ave_rim": {
      "checks": 4006,
      "consecutive_empty": 0,
      "consecutive_errors": 0,
      "last_checked_at": "2026-07-23T17:53:02.600202+00:00",
      "last_messages_count": 11,
      "last_success_at": "2026-07-23T17:53:02.600202+00:00",
      "status": "ok",
      "successful_checks": 4006
    },
    "aviciixd": {
      "checks": 6094,
      "consecutive_empty": 0,
      "consecutive_errors": 0,
      "last_checked_at": "2026-07-23T17:53:02.598650+00:00",
      "last_messages_count": 20,
      "last_success_at": "2026-07-23T17:53:02.598650+00:00",
      "status": "ok",
      "successful_checks": 6094,
      "transport_outages": 2
    },
    "avstriez": {
      "checks": 4006,
      "consecutive_empty": 0,
      "consecutive_errors": 0,
      "last_checked_at": "2026-07-23T17:53:02.600218+00:00",
      "last_messages_count": 20,
      "last_problem_at": "2026-07-20T00:00:08.160461+00:00",
      "last_success_at": "2026-07-23T17:53:02.600218+00:00",
      "status": "ok",
      "successful_checks": 4005
    },
    "ayukifunpage": {
      "checks": 1261,
      "consecutive_empty": 0,
      "consecutive_errors": 0,
      "last_checked_at": "2026-07-23T17:53:02.601205+00:00",
      "last_messages_count": 20,
      "last_success_at": "2026-07-23T17:53:02.601205+00:00",
      "status": "ok",
      "successful_checks": 1261
    },
    "bbteamcs2": {
      "checks": 5895,
      "consecutive_empty": 0,
      "consecutive_errors": 0,
      "last_checked_at": "2026-07-23T17:53:02.599297+00:00",
      "last_messages_count": 2,
      "last_success_at": "2026-07-23T17:53:02.599297+00:00",
      "status": "ok",
      "successful_checks": 5895,
      "transport_outages": 2
    },
    "beardserklife": {
      "checks": 4007,
      "consecutive_empty": 0,
      "consecutive_errors": 0,
      "last_checked_at": "2026-07-23T17:53:02.599715+00:00",
      "last_messages_count": 11,
      "last_success_at": "2026-07-23T17:53:02.599715+00:00",
      "status": "ok",
      "successful_checks": 4007
    },
    "betbistTV": {
      "checks": 5378,
      "consecutive_empty": 0,
      "consecutive_errors": 0,
      "last_checked_at": "2026-07-23T17:53:02.599663+00:00",
      "last_messages_count": 18,
      "last_problem_at": "2026-07-22T04:18:43.745866+00:00",
      "last_success_at": "2026-07-23T17:53:02.599663+00:00",
      "status": "ok",
      "successful_checks": 5377
    },
    "betboom_baza": {
      "checks": 5719,
      "consecutive_empty": 0,
      "consecutive_errors": 0,
      "last_checked_at": "2026-07-23T17:53:02.599562+00:00",
      "last_messages_count": 20,
      "last_success_at": "2026-07-23T17:53:02.599562+00:00",
      "status": "ok",
      "successful_checks": 5719
    },
    "betboom_esports": {
      "checks": 5871,
      "consecutive_empty": 0,
      "consecutive_errors": 0,
      "last_checked_at": "2026-07-23T17:53:02.599192+00:00",
      "last_messages_count": 20,
      "last_problem_at": "2026-07-23T00:56:41.680138+00:00",
      "last_success_at": "2026-07-23T17:53:02.599192+00:00",
      "status": "ok",
      "successful_checks": 5870
    },
    "betboom_esports_cs": {
      "checks": 5871,
      "consecutive_empty": 0,
      "consecutive_errors": 0,
      "last_checked_at": "2026-07-23T17:53:02.599211+00:00",
      "last_messages_count": 20,
      "last_success_at": "2026-07-23T17:53:02.599211+00:00",
      "status": "ok",
      "successful_checks": 5871
    },
    "betboomru": {
      "checks": 5871,
      "consecutive_empty": 0,
      "consecutive_errors": 0,
      "last_checked_at": "2026-07-23T17:53:02.599157+00:00",
      "last_messages_count": 20,
      "last_success_at": "2026-07-23T17:53:02.599157+00:00",
      "status": "ok",
      "successful_checks": 5871
    },
    "betboomstreamersbattle": {
      "checks": 5871,
      "consecutive_empty": 0,
      "consecutive_errors": 0,
      "last_checked_at": "2026-07-23T17:53:02.599175+00:00",
      "last_messages_count": 20,
      "last_success_at": "2026-07-23T17:53:02.599175+00:00",
      "status": "ok",
      "successful_checks": 5871
    },
    "betboomteam": {
      "checks": 5871,
      "consecutive_empty": 0,
      "consecutive_errors": 0,
      "last_checked_at": "2026-07-23T17:53:02.599245+00:00",
      "last_messages_count": 16,
      "last_success_at": "2026-07-23T17:53:02.599245+00:00",
      "status": "ok",
      "successful_checks": 5871
    },
    "betboomteamcs2": {
      "checks": 5871,
      "consecutive_empty": 0,
      "consecutive_errors": 0,
      "last_checked_at": "2026-07-23T17:53:02.599262+00:00",
      "last_messages_count": 20,
      "last_problem_at": "2026-07-23T07:57:23.751710+00:00",
      "last_success_at": "2026-07-23T17:53:02.599262+00:00",
      "status": "ok",
      "successful_checks": 5870
    },
    "bettingmedialeague": {
      "checks": 4007,
      "consecutive_empty": 0,
      "consecutive_errors": 0,
      "last_checked_at": "2026-07-23T17:53:02.599733+00:00",
      "last_messages_count": 19,
      "last_success_at": "2026-07-23T17:53:02.599733+00:00",
      "status": "ok",
      "successful_checks": 4007
    },
    "blast_betboom": {
      "checks": 5871,
      "consecutive_empty": 0,
      "consecutive_errors": 0,
      "last_checked_at": "2026-07-23T17:53:02.599227+00:00",
      "last_messages_count": 20,
      "last_success_at": "2026-07-23T17:53:02.599227+00:00",
      "status": "ok",
      "successful_checks": 5871
    },
    "blindzonexgod": {
      "checks": 6094,
      "consecutive_empty": 0,
      "consecutive_errors": 0,
      "last_checked_at": "2026-07-23T17:53:02.598982+00:00",
      "last_messages_count": 18,
      "last_success_at": "2026-07-23T17:53:02.598982+00:00",
      "status": "ok",
      "successful_checks": 6094,
      "transport_outages": 2
    },
    "boltcast": {
      "checks": 6094,
      "consecutive_empty": 0,
      "consecutive_errors": 0,
      "last_checked_at": "2026-07-23T17:53:02.598350+00:00",
      "last_messages_count": 18,
      "last_problem_at": "2026-07-19T04:15:10.911936+00:00",
      "last_success_at": "2026-07-23T17:53:02.598350+00:00",
      "status": "ok",
      "successful_checks": 6092,
      "transport_outages": 2
    },
    "burdakekw": {
      "checks": 6094,
      "consecutive_empty": 0,
      "consecutive_errors": 0,
      "last_checked_at": "2026-07-23T17:53:02.598783+00:00",
      "last_messages_count": 20,
      "last_success_at": "2026-07-23T17:53:02.598783+00:00",
      "status": "ok",
      "successful_checks": 6094,
      "transport_outages": 2
    },
    "cakestreampage": {
      "checks": 4007,
      "consecutive_empty": 0,
      "consecutive_errors": 0,
      "last_checked_at": "2026-07-23T17:53:02.599749+00:00",
      "last_messages_count": 20,
      "last_success_at": "2026-07-23T17:53:02.599749+00:00",
      "status": "ok",
      "successful_checks": 4007
    },
    "cct_betboom": {
      "checks": 1195,
      "consecutive_empty": 0,
      "consecutive_errors": 0,
      "last_checked_at": "2026-07-23T17:53:02.601239+00:00",
      "last_messages_count": 20,
      "last_success_at": "2026-07-23T17:53:02.601239+00:00",
      "status": "ok",
      "successful_checks": 1195
    },
    "chiilstreeamML": {
      "checks": 4007,
      "consecutive_empty": 0,
      "consecutive_errors": 0,
      "last_checked_at": "2026-07-23T17:53:02.599766+00:00",
      "last_messages_count": 13,
      "last_success_at": "2026-07-23T17:53:02.599766+00:00",
      "status": "ok",
      "successful_checks": 4007
    },
    "chopperinho": {
      "checks": 5378,
      "consecutive_empty": 0,
      "consecutive_errors": 0,
      "last_checked_at": "2026-07-23T17:53:02.599579+00:00",
      "last_messages_count": 7,
      "last_success_at": "2026-07-23T17:53:02.599579+00:00",
      "status": "ok",
      "successful_checks": 5378
    },
    "chopperis": {
      "checks": 6094,
      "consecutive_empty": 0,
      "consecutive_errors": 0,
      "last_checked_at": "2026-07-23T17:53:02.598573+00:00",
      "last_messages_count": 20,
      "last_success_at": "2026-07-23T17:53:02.598573+00:00",
      "status": "ok",
      "successful_checks": 6094,
      "transport_outages": 2
    },
    "clife_cs2": {
      "checks": 4006,
      "consecutive_empty": 0,
      "consecutive_errors": 0,
      "last_checked_at": "2026-07-23T17:53:02.600304+00:00",
      "last_messages_count": 13,
      "last_problem_at": "2026-07-22T07:55:40.785023+00:00",
      "last_success_at": "2026-07-23T17:53:02.600304+00:00",
      "status": "ok",
      "successful_checks": 4005
    },
    "cscis": {
      "checks": 4006,
      "consecutive_empty": 0,
      "consecutive_errors": 0,
      "last_checked_at": "2026-07-23T17:53:02.600321+00:00",
      "last_messages_count": 11,
      "last_success_at": "2026-07-23T17:53:02.600321+00:00",
      "status": "ok",
      "successful_checks": 4006
    },
    "csgobet": {
      "checks": 4006,
      "consecutive_empty": 0,
      "consecutive_errors": 0,
      "last_checked_at": "2026-07-23T17:53:02.600338+00:00",
      "last_messages_count": 20,
      "last_success_at": "2026-07-23T17:53:02.600338+00:00",
      "status": "ok",
      "successful_checks": 4006
    },
    "ct0mislove": {
      "checks": 6094,
      "consecutive_empty": 0,
      "consecutive_errors": 0,
      "last_checked_at": "2026-07-23T17:53:02.598964+00:00",
      "last_messages_count": 20,
      "last_success_at": "2026-07-23T17:53:02.598964+00:00",
      "status": "ok",
      "successful_checks": 6094,
      "transport_outages": 2
    },
    "cybercracken": {
      "checks": 4006,
      "consecutive_empty": 0,
      "consecutive_errors": 0,
      "last_checked_at": "2026-07-23T17:53:02.600355+00:00",
      "last_messages_count": 18,
      "last_problem_at": "2026-07-20T00:00:08.160597+00:00",
      "last_success_at": "2026-07-23T17:53:02.600355+00:00",
      "status": "ok",
      "successful_checks": 4005
    },
    "cyberheromlbb": {
      "checks": 4006,
      "consecutive_empty": 0,
      "consecutive_errors": 0,
      "last_checked_at": "2026-07-23T17:53:02.600389+00:00",
      "last_messages_count": 20,
      "last_problem_at": "2026-07-22T22:09:15.414128+00:00",
      "last_success_at": "2026-07-23T17:53:02.600389+00:00",
      "status": "ok",
      "successful_checks": 4005
    },
    "dadtex": {
      "checks": 3575,
      "consecutive_empty": 0,
      "consecutive_errors": 0,
      "last_checked_at": "2026-07-23T17:53:02.601102+00:00",
      "last_messages_count": 17,
      "last_success_at": "2026-07-23T17:53:02.601102+00:00",
      "status": "ok",
      "successful_checks": 3575
    },
    "danila_gorilla": {
      "checks": 6094,
      "consecutive_empty": 0,
      "consecutive_errors": 0,
      "last_checked_at": "2026-07-23T17:53:02.598707+00:00",
      "last_messages_count": 20,
      "last_problem_at": "2026-07-22T04:33:54.062847+00:00",
      "last_success_at": "2026-07-23T17:53:02.598707+00:00",
      "status": "ok",
      "successful_checks": 6093,
      "transport_outages": 2
    },
    "danzelpodval": {
      "checks": 4007,
      "consecutive_empty": 0,
      "consecutive_errors": 0,
      "last_checked_at": "2026-07-23T17:53:02.599784+00:00",
      "last_messages_count": 20,
      "last_success_at": "2026-07-23T17:53:02.599784+00:00",
      "status": "ok",
      "successful_checks": 4007
    },
    "dartwager": {
      "checks": 6094,
      "consecutive_empty": 0,
      "consecutive_errors": 0,
      "last_checked_at": "2026-07-23T17:53:02.599052+00:00",
      "last_messages_count": 18,
      "last_success_at": "2026-07-23T17:53:02.599052+00:00",
      "status": "ok",
      "successful_checks": 6094,
      "transport_outages": 2
    },
    "dayneZz": {
      "checks": 6094,
      "consecutive_empty": 0,
      "consecutive_errors": 0,
      "last_checked_at": "2026-07-23T17:53:02.598999+00:00",
      "last_messages_count": 19,
      "last_problem_at": "2026-07-21T23:07:05.355807+00:00",
      "last_success_at": "2026-07-23T17:53:02.598999+00:00",
      "status": "ok",
      "successful_checks": 6093,
      "transport_outages": 2
    },
    "dekocs": {
      "checks": 6094,
      "consecutive_empty": 0,
      "consecutive_errors": 0,
      "last_checked_at": "2026-07-23T17:53:02.598499+00:00",
      "last_messages_count": 20,
      "last_success_at": "2026-07-23T17:53:02.598499+00:00",
      "status": "ok",
      "successful_checks": 6094,
      "transport_outages": 2
    },
    "dekocsoff": {
      "checks": 6094,
      "consecutive_empty": 0,
      "consecutive_errors": 0,
      "last_checked_at": "2026-07-23T17:53:02.598947+00:00",
      "last_messages_count": 20,
      "last_success_at": "2026-07-23T17:53:02.598947+00:00",
      "status": "ok",
      "successful_checks": 6094,
      "transport_outages": 2
    },
    "dmitrylebwa": {
      "checks": 4007,
      "consecutive_empty": 0,
      "consecutive_errors": 0,
      "last_checked_at": "2026-07-23T17:53:02.599801+00:00",
      "last_messages_count": 19,
      "last_success_at": "2026-07-23T17:53:02.599801+00:00",
      "status": "ok",
      "successful_checks": 4007
    },
    "dyrachyo": {
      "checks": 6094,
      "consecutive_empty": 0,
      "consecutive_errors": 0,
      "last_checked_at": "2026-07-23T17:53:02.598260+00:00",
      "last_messages_count": 7,
      "last_problem_at": "2026-07-13T20:00:35.304945+00:00",
      "last_success_at": "2026-07-23T17:53:02.598260+00:00",
      "status": "ok",
      "successful_checks": 6093,
      "transport_outages": 2
    },
    "dyrachyobets": {
      "checks": 5378,
      "consecutive_empty": 0,
      "consecutive_errors": 0,
      "last_checked_at": "2026-07-23T17:53:02.599644+00:00",
      "last_messages_count": 19,
      "last_success_at": "2026-07-23T17:53:02.599644+00:00",
      "status": "ok",
      "successful_checks": 5378
    },
    "etozhekoval": {
      "checks": 5107,
      "consecutive_empty": 0,
      "consecutive_errors": 0,
      "last_checked_at": "2026-07-23T17:53:02.599681+00:00",
      "last_messages_count": 20,
      "last_success_at": "2026-07-23T17:53:02.599681+00:00",
      "status": "ok",
      "successful_checks": 5107
    },
    "exilemusic13": {
      "checks": 4007,
      "consecutive_empty": 0,
      "consecutive_errors": 0,
      "last_checked_at": "2026-07-23T17:53:02.599834+00:00",
      "last_messages_count": 19,
      "last_problem_at": "2026-07-23T01:09:45.180863+00:00",
      "last_success_at": "2026-07-23T17:53:02.599834+00:00",
      "status": "ok",
      "successful_checks": 4005
    },
    "f_1ncsgo": {
      "checks": 4006,
      "consecutive_empty": 0,
      "consecutive_errors": 0,
      "last_checked_at": "2026-07-23T17:53:02.600406+00:00",
      "last_messages_count": 17,
      "last_success_at": "2026-07-23T17:53:02.600406+00:00",
      "status": "ok",
      "successful_checks": 4006
    },
    "fishmandota2": {
      "checks": 4007,
      "consecutive_empty": 0,
      "consecutive_errors": 0,
      "last_checked_at": "2026-07-23T17:53:02.599851+00:00",
      "last_messages_count": 20,
      "last_success_at": "2026-07-23T17:53:02.599851+00:00",
      "status": "ok",
      "successful_checks": 4007
    },
    "flamebaker": {
      "checks": 4007,
      "consecutive_empty": 0,
      "consecutive_errors": 0,
      "last_checked_at": "2026-07-23T17:53:02.599869+00:00",
      "last_messages_count": 19,
      "last_problem_at": "2026-07-20T00:00:08.160077+00:00",
      "last_success_at": "2026-07-23T17:53:02.599869+00:00",
      "status": "ok",
      "successful_checks": 4006
    },
    "flashynthen1ght": {
      "checks": 4007,
      "consecutive_empty": 0,
      "consecutive_errors": 0,
      "last_checked_at": "2026-07-23T17:53:02.599887+00:00",
      "last_messages_count": 15,
      "last_success_at": "2026-07-23T17:53:02.599887+00:00",
      "status": "ok",
      "successful_checks": 4007
    },
    "flouzer666": {
      "checks": 4007,
      "consecutive_empty": 0,
      "consecutive_errors": 0,
      "last_checked_at": "2026-07-23T17:53:02.599904+00:00",
      "last_messages_count": 16,
      "last_problem_at": "2026-07-22T06:34:20.849059+00:00",
      "last_success_at": "2026-07-23T17:53:02.599904+00:00",
      "status": "ok",
      "successful_checks": 4005
    },
    "fmeleague": {
      "checks": 4006,
      "consecutive_empty": 0,
      "consecutive_errors": 0,
      "last_checked_at": "2026-07-23T17:53:02.600422+00:00",
      "last_messages_count": 20,
      "last_success_at": "2026-07-23T17:53:02.600422+00:00",
      "status": "ok",
      "successful_checks": 4006
    },
    "fonbetesports": {
      "checks": 4007,
      "consecutive_empty": 0,
      "consecutive_errors": 0,
      "last_checked_at": "2026-07-23T17:53:02.599922+00:00",
      "last_messages_count": 19,
      "last_success_at": "2026-07-23T17:53:02.599922+00:00",
      "status": "ok",
      "successful_checks": 4007
    },
    "fonpass": {
      "checks": 3944,
      "consecutive_empty": 0,
      "consecutive_errors": 0,
      "last_checked_at": "2026-07-23T17:53:02.601068+00:00",
      "last_messages_count": 19,
      "last_success_at": "2026-07-23T17:53:02.601068+00:00",
      "status": "ok",
      "successful_checks": 3944
    },
    "geassamlbb": {
      "checks": 4006,
      "consecutive_empty": 0,
      "consecutive_errors": 0,
      "last_checked_at": "2026-07-23T17:53:02.600440+00:00",
      "last_messages_count": 20,
      "last_success_at": "2026-07-23T17:53:02.600440+00:00",
      "status": "ok",
      "successful_checks": 4006
    },
    "gexsuntv": {
      "checks": 4006,
      "consecutive_empty": 0,
      "consecutive_errors": 0,
      "last_checked_at": "2026-07-23T17:53:02.600457+00:00",
      "last_messages_count": 20,
      "last_success_at": "2026-07-23T17:53:02.600457+00:00",
      "status": "ok",
      "successful_checks": 4006
    },
    "gluck_es": {
      "checks": 4006,
      "consecutive_empty": 0,
      "consecutive_errors": 0,
      "last_checked_at": "2026-07-23T17:53:02.600474+00:00",
      "last_messages_count": 20,
      "last_success_at": "2026-07-23T17:53:02.600474+00:00",
      "status": "ok",
      "successful_checks": 4006
    },
    "golospokera": {
      "checks": 4007,
      "consecutive_empty": 0,
      "consecutive_errors": 0,
      "last_checked_at": "2026-07-23T17:53:02.599939+00:00",
      "last_messages_count": 20,
      "last_success_at": "2026-07-23T17:53:02.599939+00:00",
      "status": "ok",
      "successful_checks": 4007
    },
    "gorilla_armor": {
      "checks": 6094,
      "consecutive_empty": 0,
      "consecutive_errors": 0,
      "last_checked_at": "2026-07-23T17:53:02.598726+00:00",
      "last_messages_count": 20,
      "last_success_at": "2026-07-23T17:53:02.598726+00:00",
      "status": "ok",
      "successful_checks": 6094,
      "transport_outages": 2
    },
    "graynetv": {
      "checks": 4006,
      "consecutive_empty": 0,
      "consecutive_errors": 0,
      "last_checked_at": "2026-07-23T17:53:02.600491+00:00",
      "last_messages_count": 14,
      "last_success_at": "2026-07-23T17:53:02.600491+00:00",
      "status": "ok",
      "successful_checks": 4006
    },
    "gshikaryan": {
      "checks": 6094,
      "consecutive_empty": 0,
      "consecutive_errors": 0,
      "last_checked_at": "2026-07-23T17:53:02.598893+00:00",
      "last_messages_count": 19,
      "last_problem_at": "2026-07-23T00:44:22.963095+00:00",
      "last_success_at": "2026-07-23T17:53:02.598893+00:00",
      "status": "ok",
      "successful_checks": 6093,
      "transport_outages": 2
    },
    "happyzerg11": {
      "checks": 4007,
      "consecutive_empty": 0,
      "consecutive_errors": 0,
      "last_checked_at": "2026-07-23T17:53:02.599974+00:00",
      "last_messages_count": 20,
      "last_success_at": "2026-07-23T17:53:02.599974+00:00",
      "status": "ok",
      "successful_checks": 4007
    },
    "helin139burmalda": {
      "checks": 73,
      "consecutive_empty": 0,
      "consecutive_errors": 0,
      "last_checked_at": "2026-07-23T17:53:02.601256+00:00",
      "last_messages_count": 20,
      "last_success_at": "2026-07-23T17:53:02.601256+00:00",
      "status": "ok",
      "successful_checks": 73
    },
    "homakolesa": {
      "checks": 6094,
      "consecutive_empty": 0,
      "consecutive_errors": 0,
      "last_checked_at": "2026-07-23T17:53:02.599017+00:00",
      "last_messages_count": 20,
      "last_success_at": "2026-07-23T17:53:02.599017+00:00",
      "status": "ok",
      "successful_checks": 6094,
      "transport_outages": 2
    },
    "hoochcs2": {
      "checks": 6094,
      "consecutive_empty": 0,
      "consecutive_errors": 0,
      "last_checked_at": "2026-07-23T17:53:02.598592+00:00",
      "last_messages_count": 19,
      "last_success_at": "2026-07-23T17:53:02.598592+00:00",
      "status": "ok",
      "successful_checks": 6094,
      "transport_outages": 2
    },
    "igmtv": {
      "checks": 4006,
      "consecutive_empty": 0,
      "consecutive_errors": 0,
      "last_checked_at": "2026-07-23T17:53:02.600508+00:00",
      "last_messages_count": 14,
      "last_success_at": "2026-07-23T17:53:02.600508+00:00",
      "status": "ok",
      "successful_checks": 4006
    },
    "ihuntnoobs": {
      "checks": 6094,
      "consecutive_empty": 0,
      "consecutive_errors": 0,
      "last_checked_at": "2026-07-23T17:53:02.598480+00:00",
      "last_messages_count": 20,
      "last_success_at": "2026-07-23T17:53:02.598480+00:00",
      "status": "ok",
      "successful_checks": 6094,
      "transport_outages": 2
    },
    "jestercast": {
      "checks": 5765,
      "consecutive_empty": 0,
      "consecutive_errors": 0,
      "last_checked_at": "2026-07-23T17:53:02.599527+00:00",
      "last_messages_count": 20,
      "last_problem_at": "2026-07-23T00:11:55.346357+00:00",
      "last_success_at": "2026-07-23T17:53:02.599527+00:00",
      "status": "ok",
      "successful_checks": 5764
    },
    "jetnizestream": {
      "checks": 4007,
      "consecutive_empty": 0,
      "consecutive_errors": 0,
      "last_checked_at": "2026-07-23T17:53:02.600009+00:00",
      "last_messages_count": 20,
      "last_problem_at": "2026-07-20T00:00:08.160236+00:00",
      "last_success_at": "2026-07-23T17:53:02.600009+00:00",
      "status": "ok",
      "successful_checks": 4006
    },
    "kdh440cast": {
      "checks": 4007,
      "consecutive_empty": 0,
      "consecutive_errors": 0,
      "last_checked_at": "2026-07-23T17:53:02.600026+00:00",
      "last_messages_count": 20,
      "last_problem_at": "2026-07-23T07:53:20.785681+00:00",
      "last_success_at": "2026-07-23T17:53:02.600026+00:00",
      "status": "ok",
      "successful_checks": 4006
    },
    "keendabol": {
      "checks": 4006,
      "consecutive_empty": 0,
      "consecutive_errors": 0,
      "last_checked_at": "2026-07-23T17:53:02.600525+00:00",
      "last_messages_count": 20,
      "last_success_at": "2026-07-23T17:53:02.600525+00:00",
      "status": "ok",
      "successful_checks": 4006
    },
    "kiraenn": {
      "checks": 4007,
      "consecutive_empty": 0,
      "consecutive_errors": 0,
      "last_checked_at": "2026-07-23T17:53:02.600043+00:00",
      "last_messages_count": 13,
      "last_success_at": "2026-07-23T17:53:02.600043+00:00",
      "status": "ok",
      "successful_checks": 4007
    },
    "kiritych1": {
      "checks": 5895,
      "consecutive_empty": 0,
      "consecutive_errors": 0,
      "last_checked_at": "2026-07-23T17:53:02.599387+00:00",
      "last_messages_count": 20,
      "last_problem_at": "2026-07-21T22:44:46.197631+00:00",
      "last_success_at": "2026-07-23T17:53:02.599387+00:00",
      "status": "ok",
      "successful_checks": 5894,
      "transport_outages": 2
    },
    "kolesaBB": {
      "checks": 6094,
      "consecutive_empty": 0,
      "consecutive_errors": 0,
      "last_checked_at": "2026-07-23T17:53:02.599087+00:00",
      "last_messages_count": 16,
      "last_success_at": "2026-07-23T17:53:02.599087+00:00",
      "status": "ok",
      "successful_checks": 6094,
      "transport_outages": 2
    },
    "kr4syy": {
      "checks": 4006,
      "consecutive_empty": 0,
      "consecutive_errors": 0,
      "last_checked_at": "2026-07-23T17:53:02.600560+00:00",
      "last_messages_count": 15,
      "last_success_at": "2026-07-23T17:53:02.600560+00:00",
      "status": "ok",
      "successful_checks": 4006
    },
    "kzmantis": {
      "checks": 6094,
      "consecutive_empty": 0,
      "consecutive_errors": 0,
      "last_checked_at": "2026-07-23T17:53:02.598838+00:00",
      "last_messages_count": 20,
      "last_success_at": "2026-07-23T17:53:02.598838+00:00",
      "status": "ok",
      "successful_checks": 6094,
      "transport_outages": 2
    },
    "ladlda": {
      "checks": 5895,
      "consecutive_empty": 0,
      "consecutive_errors": 0,
      "last_checked_at": "2026-07-23T17:53:02.599405+00:00",
      "last_messages_count": 5,
      "last_success_at": "2026-07-23T17:53:02.599405+00:00",
      "status": "ok",
      "successful_checks": 5895,
      "transport_outages": 2
    },
    "lasthero_dota": {
      "checks": 4006,
      "consecutive_empty": 0,
      "consecutive_errors": 0,
      "last_checked_at": "2026-07-23T17:53:02.600577+00:00",
      "last_messages_count": 17,
      "last_success_at": "2026-07-23T17:53:02.600577+00:00",
      "status": "ok",
      "successful_checks": 4006
    },
    "lukawahouse": {
      "checks": 5895,
      "consecutive_empty": 0,
      "consecutive_errors": 0,
      "last_checked_at": "2026-07-23T17:53:02.599422+00:00",
      "last_messages_count": 10,
      "last_success_at": "2026-07-23T17:53:02.599422+00:00",
      "status": "ok",
      "successful_checks": 5895,
      "transport_outages": 2
    },
    "m3traNeoStream": {
      "checks": 5866,
      "consecutive_empty": 0,
      "consecutive_errors": 0,
      "last_checked_at": "2026-07-23T17:53:02.599474+00:00",
      "last_messages_count": 20,
      "last_problem_at": "2026-07-21T22:41:39.930544+00:00",
      "last_success_at": "2026-07-23T17:53:02.599474+00:00",
      "status": "ok",
      "successful_checks": 5865
    },
    "m4gastreams": {
      "checks": 4006,
      "consecutive_empty": 0,
      "consecutive_errors": 0,
      "last_checked_at": "2026-07-23T17:53:02.600657+00:00",
      "last_messages_count": 20,
      "last_problem_at": "2026-07-20T00:00:08.160887+00:00",
      "last_success_at": "2026-07-23T17:53:02.600657+00:00",
      "status": "ok",
      "successful_checks": 4005
    },
    "mAger_de_nuke": {
      "checks": 6094,
      "consecutive_empty": 0,
      "consecutive_errors": 0,
      "last_checked_at": "2026-07-23T17:53:02.598518+00:00",
      "last_messages_count": 11,
      "last_problem_at": "2026-07-22T07:53:29.985173+00:00",
      "last_success_at": "2026-07-23T17:53:02.598518+00:00",
      "status": "ok",
      "successful_checks": 6093,
      "transport_outages": 2
    },
    "magnojezking": {
      "checks": 5895,
      "consecutive_empty": 0,
      "consecutive_errors": 0,
      "last_checked_at": "2026-07-23T17:53:02.599439+00:00",
      "last_messages_count": 11,
      "last_success_at": "2026-07-23T17:53:02.599439+00:00",
      "status": "ok",
      "successful_checks": 5895,
      "transport_outages": 2
    },
    "mash1nkaaa": {
      "checks": 4006,
      "consecutive_empty": 0,
      "consecutive_errors": 0,
      "last_checked_at": "2026-07-23T17:53:02.600675+00:00",
      "last_messages_count": 10,
      "last_success_at": "2026-07-23T17:53:02.600675+00:00",
      "status": "ok",
      "successful_checks": 4006
    },
    "mashiromlbb": {
      "checks": 4006,
      "consecutive_empty": 0,
      "consecutive_errors": 0,
      "last_checked_at": "2026-07-23T17:53:02.600692+00:00",
      "last_messages_count": 19,
      "last_success_at": "2026-07-23T17:53:02.600692+00:00",
      "status": "ok",
      "successful_checks": 4006
    },
    "mayakmlbb": {
      "checks": 4006,
      "consecutive_empty": 0,
      "consecutive_errors": 0,
      "last_checked_at": "2026-07-23T17:53:02.600709+00:00",
      "last_messages_count": 20,
      "last_success_at": "2026-07-23T17:53:02.600709+00:00",
      "status": "ok",
      "successful_checks": 4006
    },
    "mechanogun": {
      "checks": 6094,
      "consecutive_empty": 0,
      "consecutive_errors": 0,
      "last_checked_at": "2026-07-23T17:53:02.598199+00:00",
      "last_messages_count": 20,
      "last_problem_at": "2026-07-22T07:38:19.344659+00:00",
      "last_success_at": "2026-07-23T17:53:02.598199+00:00",
      "status": "ok",
      "successful_checks": 6091,
      "transport_outages": 2
    },
    "meowbettt": {
      "checks": 6094,
      "consecutive_empty": 0,
      "consecutive_errors": 0,
      "last_checked_at": "2026-07-23T17:53:02.598537+00:00",
      "last_messages_count": 19,
      "last_success_at": "2026-07-23T17:53:02.598537+00:00",
      "status": "ok",
      "successful_checks": 6094,
      "transport_outages": 2
    },
    "mlbbcis": {
      "checks": 4006,
      "consecutive_empty": 0,
      "consecutive_errors": 0,
      "last_checked_at": "2026-07-23T17:53:02.600726+00:00",
      "last_messages_count": 18,
      "last_success_at": "2026-07-23T17:53:02.600726+00:00",
      "status": "ok",
      "successful_checks": 4006
    },
    "mlbbesports": {
      "checks": 4006,
      "consecutive_empty": 0,
      "consecutive_errors": 0,
      "last_checked_at": "2026-07-23T17:53:02.600744+00:00",
      "last_messages_count": 16,
      "last_problem_at": "2026-07-22T14:54:10.776418+00:00",
      "last_success_at": "2026-07-23T17:53:02.600744+00:00",
      "status": "ok",
      "successful_checks": 4005
    },
    "mrdaburud": {
      "checks": 4006,
      "consecutive_empty": 0,
      "consecutive_errors": 0,
      "last_checked_at": "2026-07-23T17:53:02.600777+00:00",
      "last_messages_count": 20,
      "last_success_at": "2026-07-23T17:53:02.600777+00:00",
      "status": "ok",
      "successful_checks": 4006
    },
    "mugretnug": {
      "checks": 4007,
      "consecutive_empty": 0,
      "consecutive_errors": 0,
      "last_checked_at": "2026-07-23T17:53:02.600061+00:00",
      "last_messages_count": 16,
      "last_problem_at": "2026-07-20T00:00:08.160289+00:00",
      "last_success_at": "2026-07-23T17:53:02.600061+00:00",
      "status": "ok",
      "successful_checks": 4006
    },
    "mugretnugbet": {
      "checks": 3360,
      "consecutive_empty": 0,
      "consecutive_errors": 0,
      "last_checked_at": "2026-07-23T17:53:02.601153+00:00",
      "last_messages_count": 20,
      "last_success_at": "2026-07-23T17:53:02.601153+00:00",
      "status": "ok",
      "successful_checks": 3360
    },
    "narodCast": {
      "checks": 6094,
      "consecutive_empty": 0,
      "consecutive_errors": 0,
      "last_checked_at": "2026-07-23T17:53:02.599035+00:00",
      "last_messages_count": 20,
      "last_success_at": "2026-07-23T17:53:02.599035+00:00",
      "status": "ok",
      "successful_checks": 6094,
      "transport_outages": 2
    },
    "nixtalk": {
      "checks": 6094,
      "consecutive_empty": 0,
      "consecutive_errors": 0,
      "last_checked_at": "2026-07-23T17:53:02.598330+00:00",
      "last_messages_count": 20,
      "last_problem_at": "2026-07-13T20:00:35.305024+00:00",
      "last_success_at": "2026-07-23T17:53:02.598330+00:00",
      "status": "ok",
      "successful_checks": 6093,
      "transport_outages": 2
    },
    "nucleartigeres": {
      "checks": 1261,
      "consecutive_empty": 0,
      "consecutive_errors": 0,
      "last_checked_at": "2026-07-23T17:53:02.601222+00:00",
      "last_messages_count": 20,
      "last_success_at": "2026-07-23T17:53:02.601222+00:00",
      "status": "ok",
      "successful_checks": 1261
    },
    "obshakstaya": {
      "checks": 6094,
      "consecutive_empty": 0,
      "consecutive_errors": 0,
      "last_checked_at": "2026-07-23T17:53:02.598388+00:00",
      "last_messages_count": 20,
      "last_problem_at": "2026-07-13T20:00:35.305087+00:00",
      "last_success_at": "2026-07-23T17:53:02.598388+00:00",
      "status": "ok",
      "successful_checks": 6093,
      "transport_outages": 2
    },
    "overdrivebet": {
      "checks": 5378,
      "consecutive_empty": 0,
      "consecutive_errors": 0,
      "last_checked_at": "2026-07-23T17:53:02.599598+00:00",
      "last_messages_count": 18,
      "last_problem_at": "2026-07-23T08:06:32.332454+00:00",
      "last_success_at": "2026-07-23T17:53:02.599598+00:00",
      "status": "ok",
      "successful_checks": 5377
    },
    "pandafx": {
      "checks": 6094,
      "consecutive_empty": 0,
      "consecutive_errors": 0,
      "last_checked_at": "2026-07-23T17:53:02.598874+00:00",
      "last_messages_count": 18,
      "last_success_at": "2026-07-23T17:53:02.598874+00:00",
      "status": "ok",
      "successful_checks": 6094,
      "transport_outages": 2
    },
    "pandafx2": {
      "checks": 5871,
      "consecutive_empty": 0,
      "consecutive_errors": 0,
      "last_checked_at": "2026-07-23T17:53:02.599140+00:00",
      "last_messages_count": 19,
      "last_success_at": "2026-07-23T17:53:02.599140+00:00",
      "status": "ok",
      "successful_checks": 5871
    },
    "pokerclubsochi": {
      "checks": 4006,
      "consecutive_empty": 0,
      "consecutive_errors": 0,
      "last_checked_at": "2026-07-23T17:53:02.600794+00:00",
      "last_messages_count": 19,
      "last_success_at": "2026-07-23T17:53:02.600794+00:00",
      "status": "ok",
      "successful_checks": 4006
    },
    "realmerussia": {
      "checks": 4006,
      "consecutive_empty": 0,
      "consecutive_errors": 0,
      "last_checked_at": "2026-07-23T17:53:02.600812+00:00",
      "last_messages_count": 19,
      "last_success_at": "2026-07-23T17:53:02.600812+00:00",
      "status": "ok",
      "successful_checks": 4006
    },
    "recrent": {
      "checks": 4006,
      "consecutive_empty": 0,
      "consecutive_errors": 0,
      "last_checked_at": "2026-07-23T17:53:02.600829+00:00",
      "last_messages_count": 20,
      "last_success_at": "2026-07-23T17:53:02.600829+00:00",
      "status": "ok",
      "successful_checks": 4006
    },
    "relaxcis": {
      "checks": 6094,
      "consecutive_empty": 0,
      "consecutive_errors": 0,
      "last_checked_at": "2026-07-23T17:53:02.598801+00:00",
      "last_messages_count": 18,
      "last_success_at": "2026-07-23T17:53:02.598801+00:00",
      "status": "ok",
      "successful_checks": 6094,
      "transport_outages": 2
    },
    "risenhaha": {
      "checks": 5871,
      "consecutive_empty": 0,
      "consecutive_errors": 0,
      "last_checked_at": "2026-07-23T17:53:02.599105+00:00",
      "last_messages_count": 20,
      "last_success_at": "2026-07-23T17:53:02.599105+00:00",
      "status": "ok",
      "successful_checks": 5871
    },
    "rodjerchamp": {
      "checks": 4006,
      "consecutive_empty": 0,
      "consecutive_errors": 0,
      "last_checked_at": "2026-07-23T17:53:02.600846+00:00",
      "last_messages_count": 6,
      "last_success_at": "2026-07-23T17:53:02.600846+00:00",
      "status": "ok",
      "successful_checks": 4006
    },
    "satir_Ilya": {
      "checks": 4007,
      "consecutive_empty": 0,
      "consecutive_errors": 0,
      "last_checked_at": "2026-07-23T17:53:02.600079+00:00",
      "last_messages_count": 20,
      "last_success_at": "2026-07-23T17:53:02.600079+00:00",
      "status": "ok",
      "successful_checks": 4007
    },
    "shadowkekw": {
      "checks": 6094,
      "consecutive_empty": 0,
      "consecutive_errors": 0,
      "last_checked_at": "2026-07-23T17:53:02.598763+00:00",
      "last_messages_count": 14,
      "last_success_at": "2026-07-23T17:53:02.598763+00:00",
      "status": "ok",
      "successful_checks": 6094,
      "transport_outages": 2
    },
    "shalashshpui": {
      "checks": 4006,
      "consecutive_empty": 0,
      "consecutive_errors": 0,
      "last_checked_at": "2026-07-23T17:53:02.600880+00:00",
      "last_messages_count": 18,
      "last_problem_at": "2026-07-20T00:00:08.161105+00:00",
      "last_success_at": "2026-07-23T17:53:02.600880+00:00",
      "status": "ok",
      "successful_checks": 4005
    },
    "shalfeycsgo": {
      "checks": 4006,
      "consecutive_empty": 0,
      "consecutive_errors": 0,
      "last_checked_at": "2026-07-23T17:53:02.600897+00:00",
      "last_messages_count": 20,
      "last_success_at": "2026-07-23T17:53:02.600897+00:00",
      "status": "ok",
      "successful_checks": 4006
    },
    "sheyl31": {
      "checks": 4006,
      "consecutive_empty": 0,
      "consecutive_errors": 0,
      "last_checked_at": "2026-07-23T17:53:02.600913+00:00",
      "last_messages_count": 14,
      "last_success_at": "2026-07-23T17:53:02.600913+00:00",
      "status": "ok",
      "successful_checks": 4006
    },
    "shoke": {
      "checks": 5723,
      "consecutive_empty": 0,
      "consecutive_errors": 0,
      "last_checked_at": "2026-07-23T17:53:02.599544+00:00",
      "last_messages_count": 20,
      "last_success_at": "2026-07-23T17:53:02.599544+00:00",
      "status": "ok",
      "successful_checks": 5723
    },
    "shoketg": {
      "checks": 6094,
      "consecutive_empty": 0,
      "consecutive_errors": 0,
      "last_checked_at": "2026-07-23T17:53:02.598461+00:00",
      "last_messages_count": 20,
      "last_problem_at": "2026-07-19T04:15:10.912057+00:00",
      "last_success_at": "2026-07-23T17:53:02.598461+00:00",
      "status": "ok",
      "successful_checks": 6092,
      "transport_outages": 2
    },
    "smurf_gigachad": {
      "checks": 6094,
      "consecutive_empty": 0,
      "consecutive_errors": 0,
      "last_checked_at": "2026-07-23T17:53:02.598857+00:00",
      "last_messages_count": 18,
      "last_success_at": "2026-07-23T17:53:02.598857+00:00",
      "status": "ok",
      "successful_checks": 6094,
      "transport_outages": 2
    },
    "solo322": {
      "checks": 5378,
      "consecutive_empty": 0,
      "consecutive_errors": 0,
      "last_checked_at": "2026-07-23T17:53:02.599615+00:00",
      "last_messages_count": 20,
      "last_success_at": "2026-07-23T17:53:02.599615+00:00",
      "status": "ok",
      "successful_checks": 5378
    },
    "solo_q_q": {
      "checks": 6094,
      "consecutive_empty": 0,
      "consecutive_errors": 0,
      "last_checked_at": "2026-07-23T17:53:02.598309+00:00",
      "last_messages_count": 20,
      "last_problem_at": "2026-07-13T20:00:35.305005+00:00",
      "last_success_at": "2026-07-23T17:53:02.598309+00:00",
      "status": "ok",
      "successful_checks": 6093,
      "transport_outages": 2
    },
    "spatich": {
      "checks": 4006,
      "consecutive_empty": 0,
      "consecutive_errors": 0,
      "last_checked_at": "2026-07-23T17:53:02.600930+00:00",
      "last_messages_count": 19,
      "last_success_at": "2026-07-23T17:53:02.600930+00:00",
      "status": "ok",
      "successful_checks": 4006
    },
    "starie_seniory": {
      "checks": 5895,
      "consecutive_empty": 0,
      "consecutive_errors": 0,
      "last_checked_at": "2026-07-23T17:53:02.599457+00:00",
      "last_messages_count": 20,
      "last_success_at": "2026-07-23T17:53:02.599457+00:00",
      "status": "ok",
      "successful_checks": 5895,
      "transport_outages": 2
    },
    "stavka_tv": {
      "checks": 4007,
      "consecutive_empty": 0,
      "consecutive_errors": 0,
      "last_checked_at": "2026-07-23T17:53:02.600097+00:00",
      "last_messages_count": 20,
      "last_success_at": "2026-07-23T17:53:02.600097+00:00",
      "status": "ok",
      "successful_checks": 4007
    },
    "stavkatv": {
      "checks": 4006,
      "consecutive_empty": 0,
      "consecutive_errors": 0,
      "last_checked_at": "2026-07-23T17:53:02.600947+00:00",
      "last_messages_count": 20,
      "last_problem_at": "2026-07-20T17:12:16.079836+00:00",
      "last_success_at": "2026-07-23T17:53:02.600947+00:00",
      "status": "ok",
      "successful_checks": 4005
    },
    "streamrosstg": {
      "checks": 4007,
      "consecutive_empty": 0,
      "consecutive_errors": 0,
      "last_checked_at": "2026-07-23T17:53:02.600114+00:00",
      "last_messages_count": 13,
      "last_success_at": "2026-07-23T17:53:02.600114+00:00",
      "status": "ok",
      "successful_checks": 4007
    },
    "torycs": {
      "checks": 4006,
      "consecutive_empty": 0,
      "consecutive_errors": 0,
      "last_checked_at": "2026-07-23T17:53:02.600964+00:00",
      "last_messages_count": 14,
      "last_problem_at": "2026-07-21T23:41:46.997070+00:00",
      "last_success_at": "2026-07-23T17:53:02.600964+00:00",
      "status": "ok",
      "successful_checks": 4004
    },
    "vane4kawyhm": {
      "checks": 4006,
      "consecutive_empty": 0,
      "consecutive_errors": 0,
      "last_checked_at": "2026-07-23T17:53:02.600982+00:00",
      "last_messages_count": 12,
      "last_problem_at": "2026-07-22T05:35:54.847600+00:00",
      "last_success_at": "2026-07-23T17:53:02.600982+00:00",
      "status": "ok",
      "successful_checks": 4005
    },
    "wfksiris": {
      "checks": 4006,
      "consecutive_empty": 0,
      "consecutive_errors": 0,
      "last_checked_at": "2026-07-23T17:53:02.601017+00:00",
      "last_messages_count": 7,
      "last_success_at": "2026-07-23T17:53:02.601017+00:00",
      "status": "ok",
      "successful_checks": 4006
    },
    "whylollybet": {
      "checks": 1630,
      "consecutive_empty": 0,
      "consecutive_errors": 0,
      "last_checked_at": "2026-07-23T17:53:02.601188+00:00",
      "last_messages_count": 17,
      "last_success_at": "2026-07-23T17:53:02.601188+00:00",
      "status": "ok",
      "successful_checks": 1630
    },
    "whylollycrry": {
      "checks": 6094,
      "consecutive_empty": 0,
      "consecutive_errors": 0,
      "last_checked_at": "2026-07-23T17:53:02.598611+00:00",
      "last_messages_count": 14,
      "last_problem_at": "2026-07-19T04:15:10.912215+00:00",
      "last_success_at": "2026-07-23T17:53:02.598611+00:00",
      "status": "ok",
      "successful_checks": 6093,
      "transport_outages": 2
    },
    "wonderbelkaML": {
      "checks": 4006,
      "consecutive_empty": 0,
      "consecutive_errors": 0,
      "last_checked_at": "2026-07-23T17:53:02.601034+00:00",
      "last_messages_count": 19,
      "last_success_at": "2026-07-23T17:53:02.601034+00:00",
      "status": "ok",
      "successful_checks": 4006
    },
    "zont1x": {
      "checks": 2790,
      "consecutive_empty": 0,
      "consecutive_errors": 0,
      "last_checked_at": "2026-07-23T17:53:02.601171+00:00",
      "last_messages_count": 20,
      "last_problem_at": "2026-07-22T07:24:13.011674+00:00",
      "last_success_at": "2026-07-23T17:53:02.601171+00:00",
      "status": "ok",
      "successful_checks": 2789
    },
    "zortelad": {
      "checks": 5895,
      "consecutive_empty": 0,
      "consecutive_errors": 0,
      "last_checked_at": "2026-07-23T17:53:02.599350+00:00",
      "last_messages_count": 17,
      "last_success_at": "2026-07-23T17:53:02.599350+00:00",
      "status": "ok",
      "successful_checks": 5895,
      "transport_outages": 2
    }
  },
  "version": 1
}
