{
  "sources": {
    "AdamStaya": {
      "checks": 1977,
      "consecutive_empty": 0,
      "consecutive_errors": 0,
      "last_checked_at": "2026-07-18T09:38:55.215047+00:00",
      "last_messages_count": 16,
      "last_problem_at": "2026-07-13T20:00:35.305104+00:00",
      "last_success_at": "2026-07-18T09:38:55.215047+00:00",
      "status": "ok",
      "successful_checks": 1976,
      "transport_outages": 2
    },
    "Blindzonexbet": {
      "checks": 1977,
      "consecutive_empty": 0,
      "consecutive_errors": 0,
      "last_checked_at": "2026-07-18T09:38:55.215309+00:00",
      "last_messages_count": 19,
      "last_success_at": "2026-07-18T09:38:55.215309+00:00",
      "status": "ok",
      "successful_checks": 1977,
      "transport_outages": 2
    },
    "Breakevens": {
      "checks": 1778,
      "consecutive_empty": 0,
      "consecutive_errors": 0,
      "last_checked_at": "2026-07-18T09:38:55.215945+00:00",
      "last_messages_count": 17,
      "last_success_at": "2026-07-18T09:38:55.215945+00:00",
      "status": "ok",
      "successful_checks": 1778,
      "transport_outages": 2
    },
    "DayneezBet": {
      "checks": 1977,
      "consecutive_empty": 0,
      "consecutive_errors": 0,
      "last_checked_at": "2026-07-18T09:38:55.215327+00:00",
      "last_messages_count": 20,
      "last_success_at": "2026-07-18T09:38:55.215327+00:00",
      "status": "ok",
      "successful_checks": 1977,
      "transport_outages": 2
    },
    "EWC_betboom": {
      "checks": 1778,
      "consecutive_empty": 0,
      "consecutive_errors": 0,
      "last_checked_at": "2026-07-18T09:38:55.215997+00:00",
      "last_messages_count": 19,
      "last_success_at": "2026-07-18T09:38:55.215997+00:00",
      "status": "ok",
      "successful_checks": 1778,
      "transport_outages": 2
    },
    "False9Jersey": {
      "checks": 1778,
      "consecutive_empty": 0,
      "consecutive_errors": 0,
      "last_checked_at": "2026-07-18T09:38:55.215962+00:00",
      "last_messages_count": 6,
      "last_success_at": "2026-07-18T09:38:55.215962+00:00",
      "status": "ok",
      "successful_checks": 1778,
      "transport_outages": 2
    },
    "KRATtv": {
      "checks": 1977,
      "consecutive_empty": 0,
      "consecutive_errors": 0,
      "last_checked_at": "2026-07-18T09:38:55.215382+00:00",
      "last_messages_count": 20,
      "last_success_at": "2026-07-18T09:38:55.215382+00:00",
      "status": "ok",
      "successful_checks": 1977,
      "transport_outages": 2
    },
    "MARIOMAXTV": {
      "checks": 1651,
      "consecutive_empty": 0,
      "consecutive_errors": 0,
      "last_checked_at": "2026-07-18T09:38:55.216117+00:00",
      "last_messages_count": 20,
      "last_success_at": "2026-07-18T09:38:55.216117+00:00",
      "status": "ok",
      "successful_checks": 1651
    },
    "NeretCast": {
      "checks": 1977,
      "consecutive_empty": 0,
      "consecutive_errors": 0,
      "last_checked_at": "2026-07-18T09:38:55.215067+00:00",
      "last_messages_count": 11,
      "last_problem_at": "2026-07-13T20:00:35.305120+00:00",
      "last_success_at": "2026-07-18T09:38:55.215067+00:00",
      "status": "ok",
      "successful_checks": 1976,
      "transport_outages": 2
    },
    "PAPAdota2": {
      "checks": 1977,
      "consecutive_empty": 0,
      "consecutive_errors": 0,
      "last_checked_at": "2026-07-18T09:38:55.214927+00:00",
      "last_messages_count": 20,
      "last_problem_at": "2026-07-13T20:00:35.304970+00:00",
      "last_success_at": "2026-07-18T09:38:55.214927+00:00",
      "status": "ok",
      "successful_checks": 1976,
      "transport_outages": 2
    },
    "RelaxCisBet": {
      "checks": 1977,
      "consecutive_empty": 0,
      "consecutive_errors": 0,
      "last_checked_at": "2026-07-18T09:38:55.215456+00:00",
      "last_messages_count": 20,
      "last_success_at": "2026-07-18T09:38:55.215456+00:00",
      "status": "ok",
      "successful_checks": 1977,
      "transport_outages": 2
    },
    "StrayDungeon228": {
      "checks": 1977,
      "consecutive_empty": 0,
      "consecutive_errors": 0,
      "last_checked_at": "2026-07-18T09:38:55.215086+00:00",
      "last_messages_count": 20,
      "last_problem_at": "2026-07-13T20:00:35.305136+00:00",
      "last_success_at": "2026-07-18T09:38:55.215086+00:00",
      "status": "ok",
      "successful_checks": 1976,
      "transport_outages": 2
    },
    "YBNFedor": {
      "checks": 1754,
      "consecutive_empty": 0,
      "consecutive_errors": 0,
      "last_checked_at": "2026-07-18T09:38:55.215753+00:00",
      "last_messages_count": 19,
      "last_success_at": "2026-07-18T09:38:55.215753+00:00",
      "status": "ok",
      "successful_checks": 1754
    },
    "ZZoneRM": {
      "checks": 1977,
      "consecutive_empty": 0,
      "consecutive_errors": 0,
      "last_checked_at": "2026-07-18T09:38:55.215547+00:00",
      "last_messages_count": 20,
      "last_success_at": "2026-07-18T09:38:55.215547+00:00",
      "status": "ok",
      "successful_checks": 1977,
      "transport_outages": 2
    },
    "acoolbazarit": {
      "checks": 1977,
      "consecutive_empty": 0,
      "consecutive_errors": 0,
      "last_checked_at": "2026-07-18T09:38:55.215216+00:00",
      "last_messages_count": 16,
      "last_success_at": "2026-07-18T09:38:55.215216+00:00",
      "status": "ok",
      "successful_checks": 1977,
      "transport_outages": 2
    },
    "adekvatik": {
      "checks": 1651,
      "consecutive_empty": 0,
      "consecutive_errors": 0,
      "last_checked_at": "2026-07-18T09:38:55.216135+00:00",
      "last_messages_count": 20,
      "last_success_at": "2026-07-18T09:38:55.216135+00:00",
      "status": "ok",
      "successful_checks": 1651
    },
    "amam0610": {
      "checks": 1977,
      "consecutive_empty": 0,
      "consecutive_errors": 0,
      "last_checked_at": "2026-07-18T09:38:55.215700+00:00",
      "last_messages_count": 20,
      "last_success_at": "2026-07-18T09:38:55.215700+00:00",
      "status": "ok",
      "successful_checks": 1977,
      "transport_outages": 2
    },
    "artemkef": {
      "checks": 1778,
      "consecutive_empty": 0,
      "consecutive_errors": 0,
      "last_checked_at": "2026-07-18T09:38:55.215910+00:00",
      "last_messages_count": 19,
      "last_success_at": "2026-07-18T09:38:55.215910+00:00",
      "status": "ok",
      "successful_checks": 1778,
      "transport_outages": 2
    },
    "aunkereEZ": {
      "checks": 1977,
      "consecutive_empty": 0,
      "consecutive_errors": 0,
      "last_checked_at": "2026-07-18T09:38:55.215010+00:00",
      "last_messages_count": 18,
      "last_problem_at": "2026-07-13T20:00:35.305069+00:00",
      "last_success_at": "2026-07-18T09:38:55.215010+00:00",
      "status": "ok",
      "successful_checks": 1976,
      "transport_outages": 2
    },
    "aunkeretg": {
      "checks": 1977,
      "consecutive_empty": 0,
      "consecutive_errors": 0,
      "last_checked_at": "2026-07-18T09:38:55.215564+00:00",
      "last_messages_count": 20,
      "last_success_at": "2026-07-18T09:38:55.215564+00:00",
      "status": "ok",
      "successful_checks": 1977,
      "transport_outages": 2
    },
    "aviciixd": {
      "checks": 1977,
      "consecutive_empty": 0,
      "consecutive_errors": 0,
      "last_checked_at": "2026-07-18T09:38:55.215291+00:00",
      "last_messages_count": 20,
      "last_success_at": "2026-07-18T09:38:55.215291+00:00",
      "status": "ok",
      "successful_checks": 1977,
      "transport_outages": 2
    },
    "bbteamcs2": {
      "checks": 1778,
      "consecutive_empty": 0,
      "consecutive_errors": 0,
      "last_checked_at": "2026-07-18T09:38:55.215927+00:00",
      "last_messages_count": 2,
      "last_success_at": "2026-07-18T09:38:55.215927+00:00",
      "status": "ok",
      "successful_checks": 1778,
      "transport_outages": 2
    },
    "betbistTV": {
      "checks": 1261,
      "consecutive_empty": 0,
      "consecutive_errors": 0,
      "last_checked_at": "2026-07-18T09:38:55.216296+00:00",
      "last_messages_count": 16,
      "last_success_at": "2026-07-18T09:38:55.216296+00:00",
      "status": "ok",
      "successful_checks": 1261
    },
    "betboom_baza": {
      "checks": 1602,
      "consecutive_empty": 0,
      "consecutive_errors": 0,
      "last_checked_at": "2026-07-18T09:38:55.216205+00:00",
      "last_messages_count": 20,
      "last_success_at": "2026-07-18T09:38:55.216205+00:00",
      "status": "ok",
      "successful_checks": 1602
    },
    "betboom_esports": {
      "checks": 1754,
      "consecutive_empty": 0,
      "consecutive_errors": 0,
      "last_checked_at": "2026-07-18T09:38:55.215823+00:00",
      "last_messages_count": 20,
      "last_success_at": "2026-07-18T09:38:55.215823+00:00",
      "status": "ok",
      "successful_checks": 1754
    },
    "betboom_esports_cs": {
      "checks": 1754,
      "consecutive_empty": 0,
      "consecutive_errors": 0,
      "last_checked_at": "2026-07-18T09:38:55.215841+00:00",
      "last_messages_count": 20,
      "last_success_at": "2026-07-18T09:38:55.215841+00:00",
      "status": "ok",
      "successful_checks": 1754
    },
    "betboomru": {
      "checks": 1754,
      "consecutive_empty": 0,
      "consecutive_errors": 0,
      "last_checked_at": "2026-07-18T09:38:55.215788+00:00",
      "last_messages_count": 20,
      "last_success_at": "2026-07-18T09:38:55.215788+00:00",
      "status": "ok",
      "successful_checks": 1754
    },
    "betboomstreamersbattle": {
      "checks": 1754,
      "consecutive_empty": 0,
      "consecutive_errors": 0,
      "last_checked_at": "2026-07-18T09:38:55.215806+00:00",
      "last_messages_count": 17,
      "last_success_at": "2026-07-18T09:38:55.215806+00:00",
      "status": "ok",
      "successful_checks": 1754
    },
    "betboomteam": {
      "checks": 1754,
      "consecutive_empty": 0,
      "consecutive_errors": 0,
      "last_checked_at": "2026-07-18T09:38:55.215876+00:00",
      "last_messages_count": 19,
      "last_success_at": "2026-07-18T09:38:55.215876+00:00",
      "status": "ok",
      "successful_checks": 1754
    },
    "betboomteamcs2": {
      "checks": 1754,
      "consecutive_empty": 0,
      "consecutive_errors": 0,
      "last_checked_at": "2026-07-18T09:38:55.215893+00:00",
      "last_messages_count": 20,
      "last_success_at": "2026-07-18T09:38:55.215893+00:00",
      "status": "ok",
      "successful_checks": 1754
    },
    "blast_betboom": {
      "checks": 1754,
      "consecutive_empty": 0,
      "consecutive_errors": 0,
      "last_checked_at": "2026-07-18T09:38:55.215859+00:00",
      "last_messages_count": 20,
      "last_success_at": "2026-07-18T09:38:55.215859+00:00",
      "status": "ok",
      "successful_checks": 1754
    },
    "blindzonexgod": {
      "checks": 1977,
      "consecutive_empty": 0,
      "consecutive_errors": 0,
      "last_checked_at": "2026-07-18T09:38:55.215614+00:00",
      "last_messages_count": 18,
      "last_success_at": "2026-07-18T09:38:55.215614+00:00",
      "status": "ok",
      "successful_checks": 1977,
      "transport_outages": 2
    },
    "boltcast": {
      "checks": 1977,
      "consecutive_empty": 0,
      "consecutive_errors": 0,
      "last_checked_at": "2026-07-18T09:38:55.214991+00:00",
      "last_messages_count": 18,
      "last_problem_at": "2026-07-13T20:00:35.305051+00:00",
      "last_success_at": "2026-07-18T09:38:55.214991+00:00",
      "status": "ok",
      "successful_checks": 1976,
      "transport_outages": 2
    },
    "burdakekw": {
      "checks": 1977,
      "consecutive_empty": 0,
      "consecutive_errors": 0,
      "last_checked_at": "2026-07-18T09:38:55.215419+00:00",
      "last_messages_count": 20,
      "last_success_at": "2026-07-18T09:38:55.215419+00:00",
      "status": "ok",
      "successful_checks": 1977,
      "transport_outages": 2
    },
    "chopperinho": {
      "checks": 1261,
      "consecutive_empty": 0,
      "consecutive_errors": 0,
      "last_checked_at": "2026-07-18T09:38:55.216223+00:00",
      "last_messages_count": 7,
      "last_success_at": "2026-07-18T09:38:55.216223+00:00",
      "status": "ok",
      "successful_checks": 1261
    },
    "chopperis": {
      "checks": 1977,
      "consecutive_empty": 0,
      "consecutive_errors": 0,
      "last_checked_at": "2026-07-18T09:38:55.215235+00:00",
      "last_messages_count": 18,
      "last_success_at": "2026-07-18T09:38:55.215235+00:00",
      "status": "ok",
      "successful_checks": 1977,
      "transport_outages": 2
    },
    "ct0mislove": {
      "checks": 1977,
      "consecutive_empty": 0,
      "consecutive_errors": 0,
      "last_checked_at": "2026-07-18T09:38:55.215597+00:00",
      "last_messages_count": 19,
      "last_success_at": "2026-07-18T09:38:55.215597+00:00",
      "status": "ok",
      "successful_checks": 1977,
      "transport_outages": 2
    },
    "danila_gorilla": {
      "checks": 1977,
      "consecutive_empty": 0,
      "consecutive_errors": 0,
      "last_checked_at": "2026-07-18T09:38:55.215345+00:00",
      "last_messages_count": 15,
      "last_success_at": "2026-07-18T09:38:55.215345+00:00",
      "status": "ok",
      "successful_checks": 1977,
      "transport_outages": 2
    },
    "dartwager": {
      "checks": 1977,
      "consecutive_empty": 0,
      "consecutive_errors": 0,
      "last_checked_at": "2026-07-18T09:38:55.215683+00:00",
      "last_messages_count": 18,
      "last_success_at": "2026-07-18T09:38:55.215683+00:00",
      "status": "ok",
      "successful_checks": 1977,
      "transport_outages": 2
    },
    "dayneZz": {
      "checks": 1977,
      "consecutive_empty": 0,
      "consecutive_errors": 0,
      "last_checked_at": "2026-07-18T09:38:55.215631+00:00",
      "last_messages_count": 20,
      "last_success_at": "2026-07-18T09:38:55.215631+00:00",
      "status": "ok",
      "successful_checks": 1977,
      "transport_outages": 2
    },
    "dekocs": {
      "checks": 1977,
      "consecutive_empty": 0,
      "consecutive_errors": 0,
      "last_checked_at": "2026-07-18T09:38:55.215144+00:00",
      "last_messages_count": 20,
      "last_success_at": "2026-07-18T09:38:55.215144+00:00",
      "status": "ok",
      "successful_checks": 1977,
      "transport_outages": 2
    },
    "dekocsoff": {
      "checks": 1977,
      "consecutive_empty": 0,
      "consecutive_errors": 0,
      "last_checked_at": "2026-07-18T09:38:55.215581+00:00",
      "last_messages_count": 20,
      "last_success_at": "2026-07-18T09:38:55.215581+00:00",
      "status": "ok",
      "successful_checks": 1977,
      "transport_outages": 2
    },
    "dyrachyo": {
      "checks": 1977,
      "consecutive_empty": 0,
      "consecutive_errors": 0,
      "last_checked_at": "2026-07-18T09:38:55.214901+00:00",
      "last_messages_count": 10,
      "last_problem_at": "2026-07-13T20:00:35.304945+00:00",
      "last_success_at": "2026-07-18T09:38:55.214901+00:00",
      "status": "ok",
      "successful_checks": 1976,
      "transport_outages": 2
    },
    "dyrachyobets": {
      "checks": 1261,
      "consecutive_empty": 0,
      "consecutive_errors": 0,
      "last_checked_at": "2026-07-18T09:38:55.216279+00:00",
      "last_messages_count": 19,
      "last_success_at": "2026-07-18T09:38:55.216279+00:00",
      "status": "ok",
      "successful_checks": 1261
    },
    "etozhekoval": {
      "checks": 990,
      "consecutive_empty": 0,
      "consecutive_errors": 0,
      "last_checked_at": "2026-07-18T09:38:55.216313+00:00",
      "last_messages_count": 15,
      "last_success_at": "2026-07-18T09:38:55.216313+00:00",
      "status": "ok",
      "successful_checks": 990
    },
    "gorilla_armor": {
      "checks": 1977,
      "consecutive_empty": 0,
      "consecutive_errors": 0,
      "last_checked_at": "2026-07-18T09:38:55.215363+00:00",
      "last_messages_count": 16,
      "last_success_at": "2026-07-18T09:38:55.215363+00:00",
      "status": "ok",
      "successful_checks": 1977,
      "transport_outages": 2
    },
    "gshikaryan": {
      "checks": 1977,
      "consecutive_empty": 0,
      "consecutive_errors": 0,
      "last_checked_at": "2026-07-18T09:38:55.215529+00:00",
      "last_messages_count": 20,
      "last_success_at": "2026-07-18T09:38:55.215529+00:00",
      "status": "ok",
      "successful_checks": 1977,
      "transport_outages": 2
    },
    "homakolesa": {
      "checks": 1977,
      "consecutive_empty": 0,
      "consecutive_errors": 0,
      "last_checked_at": "2026-07-18T09:38:55.215648+00:00",
      "last_messages_count": 20,
      "last_success_at": "2026-07-18T09:38:55.215648+00:00",
      "status": "ok",
      "successful_checks": 1977,
      "transport_outages": 2
    },
    "hoochcs2": {
      "checks": 1977,
      "consecutive_empty": 0,
      "consecutive_errors": 0,
      "last_checked_at": "2026-07-18T09:38:55.215253+00:00",
      "last_messages_count": 19,
      "last_success_at": "2026-07-18T09:38:55.215253+00:00",
      "status": "ok",
      "successful_checks": 1977,
      "transport_outages": 2
    },
    "ihuntnoobs": {
      "checks": 1977,
      "consecutive_empty": 0,
      "consecutive_errors": 0,
      "last_checked_at": "2026-07-18T09:38:55.215124+00:00",
      "last_messages_count": 20,
      "last_success_at": "2026-07-18T09:38:55.215124+00:00",
      "status": "ok",
      "successful_checks": 1977,
      "transport_outages": 2
    },
    "jestercast": {
      "checks": 1648,
      "consecutive_empty": 0,
      "consecutive_errors": 0,
      "last_checked_at": "2026-07-18T09:38:55.216152+00:00",
      "last_messages_count": 20,
      "last_success_at": "2026-07-18T09:38:55.216152+00:00",
      "status": "ok",
      "successful_checks": 1648
    },
    "kiritych1": {
      "checks": 1778,
      "consecutive_empty": 0,
      "consecutive_errors": 0,
      "last_checked_at": "2026-07-18T09:38:55.216014+00:00",
      "last_messages_count": 20,
      "last_success_at": "2026-07-18T09:38:55.216014+00:00",
      "status": "ok",
      "successful_checks": 1778,
      "transport_outages": 2
    },
    "kolesaBB": {
      "checks": 1977,
      "consecutive_empty": 0,
      "consecutive_errors": 0,
      "last_checked_at": "2026-07-18T09:38:55.215718+00:00",
      "last_messages_count": 13,
      "last_success_at": "2026-07-18T09:38:55.215718+00:00",
      "status": "ok",
      "successful_checks": 1977,
      "transport_outages": 2
    },
    "kzmantis": {
      "checks": 1977,
      "consecutive_empty": 0,
      "consecutive_errors": 0,
      "last_checked_at": "2026-07-18T09:38:55.215475+00:00",
      "last_messages_count": 20,
      "last_success_at": "2026-07-18T09:38:55.215475+00:00",
      "status": "ok",
      "successful_checks": 1977,
      "transport_outages": 2
    },
    "ladlda": {
      "checks": 1778,
      "consecutive_empty": 0,
      "consecutive_errors": 0,
      "last_checked_at": "2026-07-18T09:38:55.216031+00:00",
      "last_messages_count": 5,
      "last_success_at": "2026-07-18T09:38:55.216031+00:00",
      "status": "ok",
      "successful_checks": 1778,
      "transport_outages": 2
    },
    "lukawahouse": {
      "checks": 1778,
      "consecutive_empty": 0,
      "consecutive_errors": 0,
      "last_checked_at": "2026-07-18T09:38:55.216049+00:00",
      "last_messages_count": 10,
      "last_success_at": "2026-07-18T09:38:55.216049+00:00",
      "status": "ok",
      "successful_checks": 1778,
      "transport_outages": 2
    },
    "m3traNeoStream": {
      "checks": 1749,
      "consecutive_empty": 0,
      "consecutive_errors": 0,
      "last_checked_at": "2026-07-18T09:38:55.216100+00:00",
      "last_messages_count": 20,
      "last_success_at": "2026-07-18T09:38:55.216100+00:00",
      "status": "ok",
      "successful_checks": 1749
    },
    "mAger_de_nuke": {
      "checks": 1977,
      "consecutive_empty": 0,
      "consecutive_errors": 0,
      "last_checked_at": "2026-07-18T09:38:55.215162+00:00",
      "last_messages_count": 13,
      "last_success_at": "2026-07-18T09:38:55.215162+00:00",
      "status": "ok",
      "successful_checks": 1977,
      "transport_outages": 2
    },
    "magnojezking": {
      "checks": 1778,
      "consecutive_empty": 0,
      "consecutive_errors": 0,
      "last_checked_at": "2026-07-18T09:38:55.216066+00:00",
      "last_messages_count": 20,
      "last_success_at": "2026-07-18T09:38:55.216066+00:00",
      "status": "ok",
      "successful_checks": 1778,
      "transport_outages": 2
    },
    "mechanogun": {
      "checks": 1977,
      "consecutive_empty": 0,
      "consecutive_errors": 0,
      "last_checked_at": "2026-07-18T09:38:55.214831+00:00",
      "last_messages_count": 20,
      "last_problem_at": "2026-07-13T20:00:35.304888+00:00",
      "last_success_at": "2026-07-18T09:38:55.214831+00:00",
      "status": "ok",
      "successful_checks": 1976,
      "transport_outages": 2
    },
    "meowbettt": {
      "checks": 1977,
      "consecutive_empty": 0,
      "consecutive_errors": 0,
      "last_checked_at": "2026-07-18T09:38:55.215197+00:00",
      "last_messages_count": 19,
      "last_success_at": "2026-07-18T09:38:55.215197+00:00",
      "status": "ok",
      "successful_checks": 1977,
      "transport_outages": 2
    },
    "narodCast": {
      "checks": 1977,
      "consecutive_empty": 0,
      "consecutive_errors": 0,
      "last_checked_at": "2026-07-18T09:38:55.215666+00:00",
      "last_messages_count": 20,
      "last_success_at": "2026-07-18T09:38:55.215666+00:00",
      "status": "ok",
      "successful_checks": 1977,
      "transport_outages": 2
    },
    "nixtalk": {
      "checks": 1977,
      "consecutive_empty": 0,
      "consecutive_errors": 0,
      "last_checked_at": "2026-07-18T09:38:55.214971+00:00",
      "last_messages_count": 20,
      "last_problem_at": "2026-07-13T20:00:35.305024+00:00",
      "last_success_at": "2026-07-18T09:38:55.214971+00:00",
      "status": "ok",
      "successful_checks": 1976,
      "transport_outages": 2
    },
    "obshakstaya": {
      "checks": 1977,
      "consecutive_empty": 0,
      "consecutive_errors": 0,
      "last_checked_at": "2026-07-18T09:38:55.215029+00:00",
      "last_messages_count": 20,
      "last_problem_at": "2026-07-13T20:00:35.305087+00:00",
      "last_success_at": "2026-07-18T09:38:55.215029+00:00",
      "status": "ok",
      "successful_checks": 1976,
      "transport_outages": 2
    },
    "overdrivebet": {
      "checks": 1261,
      "consecutive_empty": 0,
      "consecutive_errors": 0,
      "last_checked_at": "2026-07-18T09:38:55.216240+00:00",
      "last_messages_count": 20,
      "last_success_at": "2026-07-18T09:38:55.216240+00:00",
      "status": "ok",
      "successful_checks": 1261
    },
    "pandafx": {
      "checks": 1977,
      "consecutive_empty": 0,
      "consecutive_errors": 0,
      "last_checked_at": "2026-07-18T09:38:55.215511+00:00",
      "last_messages_count": 19,
      "last_success_at": "2026-07-18T09:38:55.215511+00:00",
      "status": "ok",
      "successful_checks": 1977,
      "transport_outages": 2
    },
    "pandafx2": {
      "checks": 1754,
      "consecutive_empty": 0,
      "consecutive_errors": 0,
      "last_checked_at": "2026-07-18T09:38:55.215770+00:00",
      "last_messages_count": 19,
      "last_success_at": "2026-07-18T09:38:55.215770+00:00",
      "status": "ok",
      "successful_checks": 1754
    },
    "relaxcis": {
      "checks": 1977,
      "consecutive_empty": 0,
      "consecutive_errors": 0,
      "last_checked_at": "2026-07-18T09:38:55.215438+00:00",
      "last_messages_count": 20,
      "last_success_at": "2026-07-18T09:38:55.215438+00:00",
      "status": "ok",
      "successful_checks": 1977,
      "transport_outages": 2
    },
    "risenhaha": {
      "checks": 1754,
      "consecutive_empty": 0,
      "consecutive_errors": 0,
      "last_checked_at": "2026-07-18T09:38:55.215736+00:00",
      "last_messages_count": 20,
      "last_success_at": "2026-07-18T09:38:55.215736+00:00",
      "status": "ok",
      "successful_checks": 1754
    },
    "shadowkekw": {
      "checks": 1977,
      "consecutive_empty": 0,
      "consecutive_errors": 0,
      "last_checked_at": "2026-07-18T09:38:55.215400+00:00",
      "last_messages_count": 14,
      "last_success_at": "2026-07-18T09:38:55.215400+00:00",
      "status": "ok",
      "successful_checks": 1977,
      "transport_outages": 2
    },
    "shoke": {
      "checks": 1606,
      "consecutive_empty": 0,
      "consecutive_errors": 0,
      "last_checked_at": "2026-07-18T09:38:55.216187+00:00",
      "last_messages_count": 20,
      "last_success_at": "2026-07-18T09:38:55.216187+00:00",
      "status": "ok",
      "successful_checks": 1606
    },
    "shoketg": {
      "checks": 1977,
      "consecutive_empty": 0,
      "consecutive_errors": 0,
      "last_checked_at": "2026-07-18T09:38:55.215104+00:00",
      "last_messages_count": 20,
      "last_problem_at": "2026-07-13T20:00:35.305153+00:00",
      "last_success_at": "2026-07-18T09:38:55.215104+00:00",
      "status": "ok",
      "successful_checks": 1976,
      "transport_outages": 2
    },
    "smurf_gigachad": {
      "checks": 1977,
      "consecutive_empty": 0,
      "consecutive_errors": 0,
      "last_checked_at": "2026-07-18T09:38:55.215493+00:00",
      "last_messages_count": 20,
      "last_success_at": "2026-07-18T09:38:55.215493+00:00",
      "status": "ok",
      "successful_checks": 1977,
      "transport_outages": 2
    },
    "solo322": {
      "checks": 1261,
      "consecutive_empty": 0,
      "consecutive_errors": 0,
      "last_checked_at": "2026-07-18T09:38:55.216257+00:00",
      "last_messages_count": 19,
      "last_success_at": "2026-07-18T09:38:55.216257+00:00",
      "status": "ok",
      "successful_checks": 1261
    },
    "solo_q_q": {
      "checks": 1977,
      "consecutive_empty": 0,
      "consecutive_errors": 0,
      "last_checked_at": "2026-07-18T09:38:55.214949+00:00",
      "last_messages_count": 20,
      "last_problem_at": "2026-07-13T20:00:35.305005+00:00",
      "last_success_at": "2026-07-18T09:38:55.214949+00:00",
      "status": "ok",
      "successful_checks": 1976,
      "transport_outages": 2
    },
    "starie_seniory": {
      "checks": 1778,
      "consecutive_empty": 0,
      "consecutive_errors": 0,
      "last_checked_at": "2026-07-18T09:38:55.216083+00:00",
      "last_messages_count": 20,
      "last_success_at": "2026-07-18T09:38:55.216083+00:00",
      "status": "ok",
      "successful_checks": 1778,
      "transport_outages": 2
    },
    "whylollycrry": {
      "checks": 1977,
      "consecutive_empty": 0,
      "consecutive_errors": 0,
      "last_checked_at": "2026-07-18T09:38:55.215271+00:00",
      "last_messages_count": 11,
      "last_success_at": "2026-07-18T09:38:55.215271+00:00",
      "status": "ok",
      "successful_checks": 1977,
      "transport_outages": 2
    },
    "zortelad": {
      "checks": 1778,
      "consecutive_empty": 0,
      "consecutive_errors": 0,
      "last_checked_at": "2026-07-18T09:38:55.215980+00:00",
      "last_messages_count": 18,
      "last_success_at": "2026-07-18T09:38:55.215980+00:00",
      "status": "ok",
      "successful_checks": 1778,
      "transport_outages": 2
    }
  },
  "version": 1
}
